mlpro_int_gymnasium/__init__.py
mlpro_int_gymnasium/boards/__init__.py
mlpro_int_gymnasium/boards/multicartpole.py
mlpro_int_gymnasium/envs/__init__.py
mlpro_int_gymnasium/envs/multicartpole.py
mlpro_int_gymnasium/wrappers/__init__.py
mlpro_int_gymnasium/wrappers/basics.py
mlpro_int_gymnasium-1.0.4.dist-info/licenses/LICENSE
mlpro_int_gymnasium-1.0.4.dist-info/METADATA
mlpro_int_gymnasium-1.0.4.dist-info/WHEEL
mlpro_int_gymnasium-1.0.4.dist-info/top_level.txt
mlpro_int_gymnasium-1.0.4.dist-info/RECORD
