Metadata-Version: 2.4
Name: mlpro-int-gymnasium
Version: 1.0.4
Summary: MLPro: Integration Gymnasium
Home-page: https://mlpro-int-gymnasium.readthedocs.io
Author: MLPro Team
Author-email: mlpro@listen.fh-swf.de
Project-URL: Bug Tracker, https://mlpro-int-gymnasium.readthedocs.io
Classifier: Programming Language :: Python :: 3
Classifier: License :: OSI Approved :: Apache Software License
Classifier: Operating System :: OS Independent
Requires-Python: >=3.11
License-File: LICENSE
Provides-Extra: full
Requires-Dist: mlpro[full]>=2.1.0; extra == "full"
Requires-Dist: gymnasium>=0.29; extra == "full"
Requires-Dist: pygame>=2.1.3; extra == "full"
Dynamic: license-file
